row64tools/__init__.py
row64tools/bytestream.py
row64tools/example.ramdb
row64tools/load_example.py
row64tools/ramdb.py
row64tools/save_example.py
row64tools-1.0.6.dist-info/METADATA
row64tools-1.0.6.dist-info/WHEEL
row64tools-1.0.6.dist-info/licenses/LICENSE
row64tools-1.0.6.dist-info/RECORD
