Metadata-Version: 2.4
Name: row64tools
Version: 1.0.6
Summary: Tools for the Row64 Platform
Project-URL: Homepage, https://github.com/Row64/row64tools
Project-URL: Bug Tracker, https://github.com/Row64/row64tools/issues
Author-email: Row64 <info@row64.com>
License-File: LICENSE
Classifier: License :: OSI Approved :: MIT License
Classifier: Operating System :: OS Independent
Classifier: Programming Language :: Python :: 3
Requires-Python: >=3.7
Requires-Dist: pandas>=1.5.0
